pycounts_farhan/__init__.py
pycounts_farhan/plotting.py
pycounts_farhan/pycounts_farhan.py
pycounts_farhan-0.1.0.dist-info/LICENSE
pycounts_farhan-0.1.0.dist-info/METADATA
pycounts_farhan-0.1.0.dist-info/WHEEL
pycounts_farhan-0.1.0.dist-info/RECORD
